hmslearn/Pubsub.py
hmslearn/__init__.py
hmslearn/edge.py
hmslearn/factor_graph.py
hmslearn/hello_world.py
hmslearn/hmm_factor_functions.py
hmslearn/main.py
hmslearn/max_product.py
hmslearn/node.py
hmslearn/node_update_functions.py
hmslearn/page_rank.py
hmslearn/reader.py
hmslearn/redis_broker.py
hmslearn/redis_callback_class.py
hmslearn/state.py
hmslearn/stop_node.py
hmslearn/sum_product.py
hmslearn/testing.py
hmslearn/user_input_functions.py
hmslearn-0.0.1.dist-info/METADATA
hmslearn-0.0.1.dist-info/RECORD
hmslearn-0.0.1.dist-info/WHEEL
hmslearn-0.0.1.dist-info/top_level.txt
