Metadata-Version: 2.1
Name: hmslearn
Version: 0.0.1
Summary: factor graph framework for machine and reinforcement learning
Home-page: https://github.com/vramesh/factor-graph-compute
Author: Andrew Yunta Tsai, Vinayak Ramesh, Devavrat Shah, Suchan Vivatsethachai
Author-email: andytsai14@gmail.com
License: MIT
Platform: UNKNOWN
